{
  "name": "string_jump_chug",
  "style": "metal",
  "difficulty": "intermediate",
  "timeSignature": "4/4",
  "bpmRange": [
    100,
    160
  ],
  "notes": [
    {
      "string": 6,
      "fret": 0,
      "beat": 1,
      "subdivision": 1,
      "duration": 1
    },
    {
      "string": 6,
      "fret": 0,
      "beat": 1,
      "subdivision": 3,
      "duration": 1
    },
    {
      "string": 5,
      "fret": 3,
      "beat": 2,
      "subdivision": 1,
      "duration": 2
    },
    {
      "string": 6,
      "fret": 0,
      "beat": 3,
      "subdivision": 1,
      "duration": 1
    },
    {
      "string": 6,
      "fret": 0,
      "beat": 3,
      "subdivision": 3,
      "duration": 1
    },
    {
      "string": 5,
      "fret": 5,
      "beat": 4,
      "subdivision": 1,
      "duration": 2
    }
  ]
}